djangoldp_newsboard/__init__.py
djangoldp_newsboard/apps.py
djangoldp_newsboard/models.py
djangoldp_newsboard/migrations/__init__.py
djangoldp_newsboard/tests/__init__.py
djangoldp_newsboard/tests/runner.py
djangoldp_newsboard/tests/tests_something.py
djangoldp_newsboard-0.1.1.dist-info/METADATA
djangoldp_newsboard-0.1.1.dist-info/WHEEL
djangoldp_newsboard-0.1.1.dist-info/top_level.txt
djangoldp_newsboard-0.1.1.dist-info/RECORD
