Metadata-Version: 2.1
Name: djangoldp-newsboard
Version: 0.1.1
Summary: djangoldp package for newsboard data models
Home-page: http://git.startinblox.com/djangoldp-packages/djangoldp-newsboard
Author: Startin'blox
Author-email: jbaptiste@hubl.world
License: MIT
Platform: UNKNOWN
Requires-Dist: djangoldp (>=2.1)
Provides-Extra: dev
Requires-Dist: factory-boy (>=2.11.0) ; extra == 'dev'
